dedalus_mcp/__init__.py
dedalus_mcp/auth/__init__.py
dedalus_mcp/cli.py
dedalus_mcp/client/__init__.py
dedalus_mcp/client/auth/__init__.py
dedalus_mcp/client/auth/authorization_code.py
dedalus_mcp/client/auth/client_credentials.py
dedalus_mcp/client/auth/device_code.py
dedalus_mcp/client/auth/discovery.py
dedalus_mcp/client/auth/models.py
dedalus_mcp/client/auth/token_exchange.py
dedalus_mcp/client/connection.py
dedalus_mcp/client/core.py
dedalus_mcp/client/error_handling.py
dedalus_mcp/client/errors.py
dedalus_mcp/client/transports.py
dedalus_mcp/completion.py
dedalus_mcp/context.py
dedalus_mcp/dispatch.py
dedalus_mcp/dpop/__init__.py
dedalus_mcp/dpop/keypair.py
dedalus_mcp/dpop/proof.py
dedalus_mcp/dpop/thumbprint.py
dedalus_mcp/dpop/validation.py
dedalus_mcp/progress.py
dedalus_mcp/prompt.py
dedalus_mcp/py.typed
dedalus_mcp/resource.py
dedalus_mcp/resource_template.py
dedalus_mcp/server/__init__.py
dedalus_mcp/server/authorization.py
dedalus_mcp/server/connectors.py
dedalus_mcp/server/core.py
dedalus_mcp/server/dependencies/__init__.py
dedalus_mcp/server/dependencies/models.py
dedalus_mcp/server/dependencies/solver.py
dedalus_mcp/server/drivers/__init__.py
dedalus_mcp/server/drivers/base.py
dedalus_mcp/server/drivers/http_api.py
dedalus_mcp/server/execution_plan.py
dedalus_mcp/server/notifications.py
dedalus_mcp/server/pagination.py
dedalus_mcp/server/resolver.py
dedalus_mcp/server/result_normalizers.py
dedalus_mcp/server/services/__init__.py
dedalus_mcp/server/services/completions.py
dedalus_mcp/server/services/connection_gate.py
dedalus_mcp/server/services/elicitation.py
dedalus_mcp/server/services/jwt_validator.py
dedalus_mcp/server/services/logging.py
dedalus_mcp/server/services/ping.py
dedalus_mcp/server/services/prompts.py
dedalus_mcp/server/services/protocols.py
dedalus_mcp/server/services/resources.py
dedalus_mcp/server/services/roots.py
dedalus_mcp/server/services/sampling.py
dedalus_mcp/server/services/tools.py
dedalus_mcp/server/subscriptions.py
dedalus_mcp-0.5.0.dist-info/WHEEL
dedalus_mcp-0.5.0.dist-info/entry_points.txt
dedalus_mcp-0.5.0.dist-info/METADATA
dedalus_mcp-0.5.0.dist-info/RECORD
