Metadata-Version: 2.3
Name: dedalus-mcp
Version: 0.5.0
Summary: A simple and performant Model Context Protocol framework for Python.
Keywords: dedalus_mcp,mcp,model context protocol,framework
Author: Dedalus Labs
Author-email: Dedalus Labs <oss@dedaluslabs.ai>
License: MIT License
Classifier: Development Status :: 3 - Alpha
Classifier: Environment :: Web Environment
Classifier: Framework :: FastAPI
Classifier: Intended Audience :: Developers
Classifier: License :: OSI Approved :: MIT License
Classifier: Operating System :: OS Independent
Classifier: Programming Language :: Python :: 3
Classifier: Programming Language :: Python :: 3.10
Classifier: Programming Language :: Python :: 3.11
Classifier: Programming Language :: Python :: 3.12
Classifier: Programming Language :: Python :: 3.13
Classifier: Topic :: Internet :: WWW/HTTP :: HTTP Servers
Classifier: Topic :: Software Development :: Libraries :: Python Modules
Classifier: Topic :: Scientific/Engineering :: Artificial Intelligence
Classifier: Typing :: Typed
Requires-Dist: pydantic>=2.12.0
Requires-Dist: mcp>=1.24.0
Requires-Dist: pyjwt[crypto]>=2.10.1
Requires-Dist: typing-extensions>=4.0.0
Requires-Dist: uvloop>=0.22.1 ; sys_platform != 'win32' and extra == 'opt'
Requires-Python: >=3.10
Project-URL: Homepage, https://github.com/dedalus-labs/dedalus-mcp-python
Project-URL: Issues, https://github.com/dedalus-labs/dedalus-mcp-python/issues
Project-URL: Repository, https://github.com/dedalus-labs/dedalus-mcp-python
Provides-Extra: opt
